tow_slack_plog/__init__.py
tow_slack_plog/slack_plog.py
tow_slack_plog-0.1.2.dist-info/METADATA
tow_slack_plog-0.1.2.dist-info/WHEEL
tow_slack_plog-0.1.2.dist-info/LICENSE
tow_slack_plog-0.1.2.dist-info/RECORD
