Metadata-Version: 2.1
Name: tow-slack-plog
Version: 0.1.2
Summary: 
Author: Fhuad Balogun
Author-email: fhuadbalogun@gmail.com
Requires-Python: >=3.8,<4.0
Classifier: Programming Language :: Python :: 3
Classifier: Programming Language :: Python :: 3.8
Classifier: Programming Language :: Python :: 3.9
Classifier: Programming Language :: Python :: 3.10
Classifier: Programming Language :: Python :: 3.11
Requires-Dist: slack-sdk (>=3.20.0,<4.0.0)
